autorecsys/__init__.py
autorecsys/auto_search.py
autorecsys/recommender.py
autorecsys/pipeline/__init__.py
autorecsys/pipeline/base.py
autorecsys/pipeline/graph.py
autorecsys/pipeline/interactor.py
autorecsys/pipeline/mapper.py
autorecsys/pipeline/node.py
autorecsys/pipeline/optimizer.py
autorecsys/pipeline/preprocessor.py
autorecsys/pipeline/utils.py
autorecsys/searcher/__init__.py
autorecsys/searcher/core/__init__.py
autorecsys/searcher/core/hyperparameters.py
autorecsys/searcher/core/oracle.py
autorecsys/searcher/core/trial.py
autorecsys/searcher/core/utils.py
autorecsys/searcher/tuners/__init__.py
autorecsys/searcher/tuners/bayesian.py
autorecsys/searcher/tuners/greedy.py
autorecsys/searcher/tuners/randomsearch.py
autorecsys/searcher/tuners/tuner.py
autorecsys/utils/__init__.py
autorecsys/utils/common.py
autorecsys/utils/display.py
autorecsys/utils/metric.py
autorecsys-0.0.1.dist-info/METADATA
autorecsys-0.0.1.dist-info/WHEEL
autorecsys-0.0.1.dist-info/top_level.txt
autorecsys-0.0.1.dist-info/RECORD
